[
  {
    "id": "eco-mug-001",
    "name": "Eco-Friendly Bamboo Mug",
    "description": "A stylish and sustainable mug made from natural bamboo fibers, perfect for your daily coffee or tea. Dishwasher safe and biodegradable.",
    "tags": [
      "eco-friendly",
      "home-goods",
      "kitchenware",
      "sustainable"
    ],
    "main_image": "https://picsum.photos/id/237/400/300",
    "secondary_images": [
      "https://picsum.photos/id/257/400/300",
      "https://picsum.photos/id/1060/400/300"
    ],
    "size": "350ml",
    "quantity": 50,
    "price": 12.99,
    "reviews": [
      {
        "customer_name": "Sarah P.",
        "rating": 5,
        "comment": "Love this mug! It's lightweight and looks great."
      },
      {
        "customer_name": "boy",
        "rating": 5,
        "comment": "thats a dog"
      },
      {
        "customer_name": "boy",
        "rating": 4,
        "comment": "black colored dog"
      },
      {
        "customer_name": "boy",
        "rating": 1,
        "comment": "one more review"
      }
    ],
    "material": "Bamboo Fiber",
    "additional_info": [
      {
        "title": "Care",
        "description": "Hand wash recommended"
      },
      {
        "title": "Care",
        "description": "Hand wash recommended"
      },
      {
        "title": "Care",
        "description": "Hand wash recommended"
      },
      {
        "title": "Care",
        "description": "Hand wash recommended"
      }
    ]
  },
  {
    "id": "smart-led-strip-004",
    "name": "Smart RGB LED Strip Lights",
    "description": "Transform your space with vibrant, customizable lighting. Control via app or voice assistant, perfect for ambient or accent lighting.",
    "tags": [
      "electronics",
      "smart-home",
      "lighting",
      "gadget"
    ],
    "main_image": "https://picsum.photos/id/257/400/300",
    "secondary_images": [
      "https://picsum.photos/id/237/400/300",
      "https://picsum.photos/id/196/400/300"
    ],
    "size": "5m",
    "quantity": 120,
    "price": 29.99,
    "reviews": [
      {
        "customer_name": "Tom H.",
        "rating": 4,
        "comment": "Easy to install and the colors are amazing."
      }
    ],
    "material": "Plastic",
    "additional_info": [
      {
        "title": "Features",
        "description": "16 million colors,Wi-Fi enabled"
      }
    ]
  },
  {
    "id": "yoga-mat-006",
    "name": "Eco-Grip Yoga Mat",
    "description": "High-performance yoga mat offering superior grip and cushioning. Made from sustainable, non-toxic materials for your mindful practice.",
    "tags": [
      "fitness",
      "eco-friendly",
      "wellness",
      "sports"
    ],
    "main_image": "https://picsum.photos/id/1060/400/300",
    "secondary_images": [
      "https://picsum.photos/id/196/400/300",
      "https://picsum.photos/id/237/400/300"
    ],
    "size": "183cm x 61cm",
    "quantity": 75,
    "price": 39.5,
    "reviews": [
      {
        "customer_name": "Lisa M.",
        "rating": 5,
        "comment": "The grip is fantastic, I feel very stable during my poses."
      }
    ],
    "material": "Natural Rubber",
    "additional_info": [
      {
        "title": "Thickness",
        "description": "6mm"
      },
      {
        "title": "Color",
        "description": "Forest Green"
      }
    ]
  },
  {
    "id": "ceramic-planter-007",
    "name": "Minimalist Ceramic Planter",
    "description": "Elegantly designed ceramic planter, perfect for bringing a touch of greenery indoors. Features a drainage hole and saucer.",
    "tags": [
      "home-decor",
      "gardening",
      "minimalist",
      "ceramic"
    ],
    "main_image": "https://picsum.photos/id/196/400/300",
    "secondary_images": [
      "https://picsum.photos/id/1060/400/300",
      "https://picsum.photos/id/257/400/300"
    ],
    "size": "20cm diameter",
    "quantity": 30,
    "price": 22,
    "reviews": [
      {
        "customer_name": "Mark D.",
        "rating": 4,
        "comment": "Looks great on my windowsill. The quality is solid."
      }
    ],
    "material": "Ceramic",
    "additional_info": [
      {
        "title": "Finish",
        "description": "Matte White"
      },
      {
        "title": "Includes",
        "description": "Drainage saucer"
      }
    ]
  },
  {
    "id": "bcecd106-313c-48da-9c90-60bf9acefb4c",
    "name": "drawing",
    "description": "d",
    "tags": [
      "seo",
      "pyramid"
    ],
    "main_image": "/images/2a3fb3e3-80a1-48d0-a5f5-3a3521019239-wire frame.jpg",
    "secondary_images": [
      "https://picsum.photos/id/237/400/300",
      "https://picsum.photos/id/257/400/300"
    ],
    "size": "A4",
    "quantity": 10,
    "price": 15,
    "reviews": [],
    "material": "Paper",
    "additional_info": [
      {
        "title": "Style",
        "description": "Sketch"
      },
      {
        "title": "Artist",
        "description": "Local Artist"
      }
    ]
  },
  {
    "id": "test-2-wireframe-c0979fb3",
    "name": "test-2 wireframe",
    "description": "no",
    "main_image": "/images/620c54d5-106e-4ef9-98da-450666dacb9b-wire frame.jpg",
    "secondary_images": [
      "/images/a4ed4534-674e-4196-a2ed-5ea6b9857bee-seo-pyramid-and-all-seo-components-1200x675.png.webp",
      "/images/1f2978eb-5922-410f-96e8-966cd2b0b63f-wire frame.jpg"
    ],
    "tags": [
      "seo",
      "pyramid"
    ],
    "price": 0,
    "size": "9999 inches",
    "quantity": 0,
    "reviews": [],
    "material": "paper",
    "additional_info": [
      {
        "title": "title-wireframe-on-paper",
        "description": "desc-wireframe-for the website"
      }
    ]
  },
  {
    "id": "anime-9d6a2696",
    "name": "Anime",
    "description": "adsf",
    "main_image": "/images/8b7c3c9c-8f77-4b17-a02e-dbe84f80f24e-seo-pyramid-and-all-seo-components-1200x675.png.webp",
    "secondary_images": [
      "/images/c5db181d-0789-4fb1-819f-eed4c62a29b3-seo-pyramid-and-all-seo-components-1200x675.png.webp",
      "/images/c9f690ab-b69b-41bf-8409-6eb98694e589-wire frame.jpg"
    ],
    "tags": [
      "seo",
      "pyramid"
    ],
    "price": 1,
    "size": "1",
    "quantity": 0,
    "reviews": [],
    "material": "1",
    "additional_info": [
      {
        "title": "1",
        "description": "2"
      }
    ]
  },
  {
    "id": "aa-7eff67f3",
    "name": "aa",
    "description": "aa",
    "main_image": "/images/b70d8e53-7624-4202-b22c-e2c56ddc1495-wire frame.jpg",
    "secondary_images": [
      "/images/78620c78-beb5-4c1d-ab60-6d8a2c490ddd-seo-pyramid-and-all-seo-components-1200x675.png.webp",
      "/images/4d10d911-37b5-47a3-b8e8-a9dab539525d-wire frame.jpg"
    ],
    "tags": [
      "seo",
      "pyramid"
    ],
    "price": 1,
    "size": "xl",
    "quantity": 999,
    "reviews": [],
    "material": "sd",
    "additional_info": [
      {
        "title": "ad",
        "description": "ada"
      }
    ]
  },
  {
    "id": "abcd-1ebf6860",
    "name": "abcd",
    "description": "efg",
    "main_image": "/images/51bf3332-07c7-4e8e-aa0c-df8a5379d6a3-wire frame.jpg",
    "secondary_images": [
      "/images/13ed173c-3a5f-4713-9332-c226d68221da-seo-pyramid-and-all-seo-components-1200x675.png.webp"
    ],
    "tags": [
      "ceramic",
      "eco-friendly",
      "electronics",
      "fitness",
      "gadget",
      "gardening",
      "lighting",
      "new"
    ],
    "price": 11,
    "size": "11",
    "quantity": 11,
    "reviews": [],
    "material": "11",
    "additional_info": [
      {
        "title": "fish",
        "description": "can roll"
      },
      {
        "title": "crystal",
        "description": "can sheild"
      },
      {
        "title": "plant",
        "description": "can snear"
      }
    ]
  },
  {
    "id": "test-for-webp-0b83b29d",
    "name": "test for webp",
    "description": "dsaf1",
    "main_image": "/images/test-for-webp-fab5abdf-50fa-47d0-99d7-2b5e70fe0710.webp",
    "secondary_images": [
      "/images/test-for-webp-d05b3c95-370f-4462-86e9-4f11c779f26b.webp",
      "/images/test-for-webp-15a78eb5-43fb-44e3-a789-453cd5e85f10.webp",
      "/images/test-for-webp-c477b57b-4e61-445c-bd72-3c5ca0be92b8.webp",
      "/images/test-for-webp-1008680e-d943-4576-9727-a505983a5423.webp"
    ],
    "tags": [
      "ceramic",
      "new"
    ],
    "price": 110.98,
    "size": "11111",
    "quantity": 111,
    "reviews": [],
    "material": "1",
    "additional_info": [
      {
        "title": "1",
        "description": "1"
      }
    ]
  }
]